{
  "format": "panels_2d",
  "description": "Unit square centered at origin with 4 panels per side (16 total)",
  "nodes": [
    [-0.5, -0.5, 0.0],
    [-0.25, -0.5, 0.0],
    [0.0, -0.5, 0.0],
    [0.25, -0.5, 0.0],
    [0.5, -0.5, 0.0],
    [0.5, -0.25, 0.0],
    [0.5, 0.0, 0.0],
    [0.5, 0.25, 0.0],
    [0.5, 0.5, 0.0],
    [0.25, 0.5, 0.0],
    [0.0, 0.5, 0.0],
    [-0.25, 0.5, 0.0],
    [-0.5, 0.5, 0.0],
    [-0.5, 0.25, 0.0],
    [-0.5, 0.0, 0.0],
    [-0.5, -0.25, 0.0]
  ],
  "panels": [
    [0, 1], [1, 2], [2, 3], [3, 4],
    [4, 5], [5, 6], [6, 7], [7, 8],
    [8, 9], [9, 10], [10, 11], [11, 12],
    [12, 13], [13, 14], [14, 15], [15, 0]
  ],
  "normal_direction": "outward"
}
